<?xml version="1.0" encoding="UTF-8"?>
<!DOCTYPE mapper PUBLIC "-//mybatis.org//DTD Mapper 3.0//EN" "http://mybatis.org/dtd/mybatis-3-mapper.dtd">
<mapper namespace="com.x.ic.msg.dao.mapper.interfaces.StlPolicyTaskCycleMapper">
  <resultMap id="BaseResultMap" type="com.x.ic.msg.dao.mapper.bo.StlPolicyTaskCycle">
    <!--
      WARNING - @mbg.generated
      This element is automatically generated by MyBatis Generator, do not modify.
      This element was generated on Fri Aug 03 16:38:50 CST 2018.
    -->
    <id column="POLICY_CYCLE_ID" jdbcType="VARCHAR" property="policyCycleId" />
    <result column="POLICY_CYCLE_CODE" jdbcType="VARCHAR" property="policyCycleCode" />
    <result column="POLICY_ID" jdbcType="BIGINT" property="policyId" />
    <result column="OBJECT_TYPE" jdbcType="VARCHAR" property="objectType" />
    <result column="OBJECT_CODE" jdbcType="VARCHAR" property="objectCode" />
    <result column="START_TIME" jdbcType="TIMESTAMP" property="startTime" />
    <result column="END_TIME" jdbcType="TIMESTAMP" property="endTime" />
    <result column="STATUS" jdbcType="VARCHAR" property="status" />
    <result column="TENANT_ID" jdbcType="VARCHAR" property="tenantId" />
    <result column="CREATE_DATE" jdbcType="TIMESTAMP" property="createDate" />
    <result column="UPDATE_TIME" jdbcType="TIMESTAMP" property="updateTime" />
    <result column="CREATE_STAFF_ID" jdbcType="VARCHAR" property="createStaffId" />
    <result column="CYCLE_VALUE" jdbcType="VARCHAR" property="cycleValue" />
  </resultMap>
  <sql id="Example_Where_Clause">
    <!--
      WARNING - @mbg.generated
      This element is automatically generated by MyBatis Generator, do not modify.
      This element was generated on Fri Aug 03 16:38:50 CST 2018.
    -->
    <where>
      <foreach collection="oredCriteria" item="criteria" separator="or">
        <if test="criteria.valid">
          <trim prefix="(" prefixOverrides="and" suffix=")">
            <foreach collection="criteria.criteria" item="criterion">
              <choose>
                <when test="criterion.noValue">
                  and ${criterion.condition}
                </when>
                <when test="criterion.singleValue">
                  and ${criterion.condition} #{criterion.value}
                </when>
                <when test="criterion.betweenValue">
                  and ${criterion.condition} #{criterion.value} and #{criterion.secondValue}
                </when>
                <when test="criterion.listValue">
                  and ${criterion.condition}
                  <foreach close=")" collection="criterion.value" item="listItem" open="(" separator=",">
                    #{listItem}
                  </foreach>
                </when>
              </choose>
            </foreach>
          </trim>
        </if>
      </foreach>
    </where>
  </sql>
  <sql id="Update_By_Example_Where_Clause">
    <!--
      WARNING - @mbg.generated
      This element is automatically generated by MyBatis Generator, do not modify.
      This element was generated on Fri Aug 03 16:38:50 CST 2018.
    -->
    <where>
      <foreach collection="example.oredCriteria" item="criteria" separator="or">
        <if test="criteria.valid">
          <trim prefix="(" prefixOverrides="and" suffix=")">
            <foreach collection="criteria.criteria" item="criterion">
              <choose>
                <when test="criterion.noValue">
                  and ${criterion.condition}
                </when>
                <when test="criterion.singleValue">
                  and ${criterion.condition} #{criterion.value}
                </when>
                <when test="criterion.betweenValue">
                  and ${criterion.condition} #{criterion.value} and #{criterion.secondValue}
                </when>
                <when test="criterion.listValue">
                  and ${criterion.condition}
                  <foreach close=")" collection="criterion.value" item="listItem" open="(" separator=",">
                    #{listItem}
                  </foreach>
                </when>
              </choose>
            </foreach>
          </trim>
        </if>
      </foreach>
    </where>
  </sql>
  <sql id="Base_Column_List">
    <!--
      WARNING - @mbg.generated
      This element is automatically generated by MyBatis Generator, do not modify.
      This element was generated on Fri Aug 03 16:38:50 CST 2018.
    -->
    POLICY_CYCLE_ID, POLICY_CYCLE_CODE, POLICY_ID, OBJECT_TYPE, OBJECT_CODE, START_TIME, 
    END_TIME, STATUS, TENANT_ID, CREATE_DATE, UPDATE_TIME, CREATE_STAFF_ID, CYCLE_VALUE
  </sql>
  <select id="selectByExample" parameterType="com.x.ic.msg.dao.mapper.bo.StlPolicyTaskCycleExample" resultMap="BaseResultMap">
    <!--
      WARNING - @mbg.generated
      This element is automatically generated by MyBatis Generator, do not modify.
      This element was generated on Fri Aug 03 16:38:50 CST 2018.
    -->
    select
    <if test="distinct">
      distinct
    </if>
    <include refid="Base_Column_List" />
    from stl_policy_task_cycle
    <if test="_parameter != null">
      <include refid="Example_Where_Clause" />
    </if>
    <if test="orderByClause != null">
      order by ${orderByClause}
    </if>
  </select>
  <select id="selectByPrimaryKey" parameterType="java.lang.String" resultMap="BaseResultMap">
    <!--
      WARNING - @mbg.generated
      This element is automatically generated by MyBatis Generator, do not modify.
      This element was generated on Fri Aug 03 16:38:50 CST 2018.
    -->
    select 
    <include refid="Base_Column_List" />
    from stl_policy_task_cycle
    where POLICY_CYCLE_ID = #{policyCycleId,jdbcType=VARCHAR}
  </select>
  <delete id="deleteByPrimaryKey" parameterType="java.lang.String">
    <!--
      WARNING - @mbg.generated
      This element is automatically generated by MyBatis Generator, do not modify.
      This element was generated on Fri Aug 03 16:38:50 CST 2018.
    -->
    delete from stl_policy_task_cycle
    where POLICY_CYCLE_ID = #{policyCycleId,jdbcType=VARCHAR}
  </delete>
  <delete id="deleteByExample" parameterType="com.x.ic.msg.dao.mapper.bo.StlPolicyTaskCycleExample">
    <!--
      WARNING - @mbg.generated
      This element is automatically generated by MyBatis Generator, do not modify.
      This element was generated on Fri Aug 03 16:38:50 CST 2018.
    -->
    delete from stl_policy_task_cycle
    <if test="_parameter != null">
      <include refid="Example_Where_Clause" />
    </if>
  </delete>
  <insert id="insert" parameterType="com.x.ic.msg.dao.mapper.bo.StlPolicyTaskCycle">
    <!--
      WARNING - @mbg.generated
      This element is automatically generated by MyBatis Generator, do not modify.
      This element was generated on Fri Aug 03 16:38:50 CST 2018.
    -->
    insert into stl_policy_task_cycle (POLICY_CYCLE_ID, POLICY_CYCLE_CODE, POLICY_ID, 
      OBJECT_TYPE, OBJECT_CODE, START_TIME, 
      END_TIME, STATUS, TENANT_ID, 
      CREATE_DATE, UPDATE_TIME, CREATE_STAFF_ID, 
      CYCLE_VALUE)
    values (#{policyCycleId,jdbcType=VARCHAR}, #{policyCycleCode,jdbcType=VARCHAR}, #{policyId,jdbcType=BIGINT}, 
      #{objectType,jdbcType=VARCHAR}, #{objectCode,jdbcType=VARCHAR}, #{startTime,jdbcType=TIMESTAMP}, 
      #{endTime,jdbcType=TIMESTAMP}, #{status,jdbcType=VARCHAR}, #{tenantId,jdbcType=VARCHAR}, 
      #{createDate,jdbcType=TIMESTAMP}, #{updateTime,jdbcType=TIMESTAMP}, #{createStaffId,jdbcType=VARCHAR}, 
      #{cycleValue,jdbcType=VARCHAR})
  </insert>
  <insert id="insertSelective" parameterType="com.x.ic.msg.dao.mapper.bo.StlPolicyTaskCycle">
    <!--
      WARNING - @mbg.generated
      This element is automatically generated by MyBatis Generator, do not modify.
      This element was generated on Fri Aug 03 16:38:50 CST 2018.
    -->
    insert into stl_policy_task_cycle
    <trim prefix="(" suffix=")" suffixOverrides=",">
      <if test="policyCycleId != null">
        POLICY_CYCLE_ID,
      </if>
      <if test="policyCycleCode != null">
        POLICY_CYCLE_CODE,
      </if>
      <if test="policyId != null">
        POLICY_ID,
      </if>
      <if test="objectType != null">
        OBJECT_TYPE,
      </if>
      <if test="objectCode != null">
        OBJECT_CODE,
      </if>
      <if test="startTime != null">
        START_TIME,
      </if>
      <if test="endTime != null">
        END_TIME,
      </if>
      <if test="status != null">
        STATUS,
      </if>
      <if test="tenantId != null">
        TENANT_ID,
      </if>
      <if test="createDate != null">
        CREATE_DATE,
      </if>
      <if test="updateTime != null">
        UPDATE_TIME,
      </if>
      <if test="createStaffId != null">
        CREATE_STAFF_ID,
      </if>
      <if test="cycleValue != null">
        CYCLE_VALUE,
      </if>
    </trim>
    <trim prefix="values (" suffix=")" suffixOverrides=",">
      <if test="policyCycleId != null">
        #{policyCycleId,jdbcType=VARCHAR},
      </if>
      <if test="policyCycleCode != null">
        #{policyCycleCode,jdbcType=VARCHAR},
      </if>
      <if test="policyId != null">
        #{policyId,jdbcType=BIGINT},
      </if>
      <if test="objectType != null">
        #{objectType,jdbcType=VARCHAR},
      </if>
      <if test="objectCode != null">
        #{objectCode,jdbcType=VARCHAR},
      </if>
      <if test="startTime != null">
        #{startTime,jdbcType=TIMESTAMP},
      </if>
      <if test="endTime != null">
        #{endTime,jdbcType=TIMESTAMP},
      </if>
      <if test="status != null">
        #{status,jdbcType=VARCHAR},
      </if>
      <if test="tenantId != null">
        #{tenantId,jdbcType=VARCHAR},
      </if>
      <if test="createDate != null">
        #{createDate,jdbcType=TIMESTAMP},
      </if>
      <if test="updateTime != null">
        #{updateTime,jdbcType=TIMESTAMP},
      </if>
      <if test="createStaffId != null">
        #{createStaffId,jdbcType=VARCHAR},
      </if>
      <if test="cycleValue != null">
        #{cycleValue,jdbcType=VARCHAR},
      </if>
    </trim>
  </insert>
  <select id="countByExample" parameterType="com.x.ic.msg.dao.mapper.bo.StlPolicyTaskCycleExample" resultType="java.lang.Long">
    <!--
      WARNING - @mbg.generated
      This element is automatically generated by MyBatis Generator, do not modify.
      This element was generated on Fri Aug 03 16:38:50 CST 2018.
    -->
    select count(*) from stl_policy_task_cycle
    <if test="_parameter != null">
      <include refid="Example_Where_Clause" />
    </if>
  </select>
  <update id="updateByExampleSelective" parameterType="map">
    <!--
      WARNING - @mbg.generated
      This element is automatically generated by MyBatis Generator, do not modify.
      This element was generated on Fri Aug 03 16:38:50 CST 2018.
    -->
    update stl_policy_task_cycle
    <set>
      <if test="record.policyCycleId != null">
        POLICY_CYCLE_ID = #{record.policyCycleId,jdbcType=VARCHAR},
      </if>
      <if test="record.policyCycleCode != null">
        POLICY_CYCLE_CODE = #{record.policyCycleCode,jdbcType=VARCHAR},
      </if>
      <if test="record.policyId != null">
        POLICY_ID = #{record.policyId,jdbcType=BIGINT},
      </if>
      <if test="record.objectType != null">
        OBJECT_TYPE = #{record.objectType,jdbcType=VARCHAR},
      </if>
      <if test="record.objectCode != null">
        OBJECT_CODE = #{record.objectCode,jdbcType=VARCHAR},
      </if>
      <if test="record.startTime != null">
        START_TIME = #{record.startTime,jdbcType=TIMESTAMP},
      </if>
      <if test="record.endTime != null">
        END_TIME = #{record.endTime,jdbcType=TIMESTAMP},
      </if>
      <if test="record.status != null">
        STATUS = #{record.status,jdbcType=VARCHAR},
      </if>
      <if test="record.tenantId != null">
        TENANT_ID = #{record.tenantId,jdbcType=VARCHAR},
      </if>
      <if test="record.createDate != null">
        CREATE_DATE = #{record.createDate,jdbcType=TIMESTAMP},
      </if>
      <if test="record.updateTime != null">
        UPDATE_TIME = #{record.updateTime,jdbcType=TIMESTAMP},
      </if>
      <if test="record.createStaffId != null">
        CREATE_STAFF_ID = #{record.createStaffId,jdbcType=VARCHAR},
      </if>
      <if test="record.cycleValue != null">
        CYCLE_VALUE = #{record.cycleValue,jdbcType=VARCHAR},
      </if>
    </set>
    <if test="_parameter != null">
      <include refid="Update_By_Example_Where_Clause" />
    </if>
  </update>
  <update id="updateByExample" parameterType="map">
    <!--
      WARNING - @mbg.generated
      This element is automatically generated by MyBatis Generator, do not modify.
      This element was generated on Fri Aug 03 16:38:50 CST 2018.
    -->
    update stl_policy_task_cycle
    set POLICY_CYCLE_ID = #{record.policyCycleId,jdbcType=VARCHAR},
      POLICY_CYCLE_CODE = #{record.policyCycleCode,jdbcType=VARCHAR},
      POLICY_ID = #{record.policyId,jdbcType=BIGINT},
      OBJECT_TYPE = #{record.objectType,jdbcType=VARCHAR},
      OBJECT_CODE = #{record.objectCode,jdbcType=VARCHAR},
      START_TIME = #{record.startTime,jdbcType=TIMESTAMP},
      END_TIME = #{record.endTime,jdbcType=TIMESTAMP},
      STATUS = #{record.status,jdbcType=VARCHAR},
      TENANT_ID = #{record.tenantId,jdbcType=VARCHAR},
      CREATE_DATE = #{record.createDate,jdbcType=TIMESTAMP},
      UPDATE_TIME = #{record.updateTime,jdbcType=TIMESTAMP},
      CREATE_STAFF_ID = #{record.createStaffId,jdbcType=VARCHAR},
      CYCLE_VALUE = #{record.cycleValue,jdbcType=VARCHAR}
    <if test="_parameter != null">
      <include refid="Update_By_Example_Where_Clause" />
    </if>
  </update>
  <update id="updateByPrimaryKeySelective" parameterType="com.x.ic.msg.dao.mapper.bo.StlPolicyTaskCycle">
    <!--
      WARNING - @mbg.generated
      This element is automatically generated by MyBatis Generator, do not modify.
      This element was generated on Fri Aug 03 16:38:50 CST 2018.
    -->
    update stl_policy_task_cycle
    <set>
      <if test="policyCycleCode != null">
        POLICY_CYCLE_CODE = #{policyCycleCode,jdbcType=VARCHAR},
      </if>
      <if test="policyId != null">
        POLICY_ID = #{policyId,jdbcType=BIGINT},
      </if>
      <if test="objectType != null">
        OBJECT_TYPE = #{objectType,jdbcType=VARCHAR},
      </if>
      <if test="objectCode != null">
        OBJECT_CODE = #{objectCode,jdbcType=VARCHAR},
      </if>
      <if test="startTime != null">
        START_TIME = #{startTime,jdbcType=TIMESTAMP},
      </if>
      <if test="endTime != null">
        END_TIME = #{endTime,jdbcType=TIMESTAMP},
      </if>
      <if test="status != null">
        STATUS = #{status,jdbcType=VARCHAR},
      </if>
      <if test="tenantId != null">
        TENANT_ID = #{tenantId,jdbcType=VARCHAR},
      </if>
      <if test="createDate != null">
        CREATE_DATE = #{createDate,jdbcType=TIMESTAMP},
      </if>
      <if test="updateTime != null">
        UPDATE_TIME = #{updateTime,jdbcType=TIMESTAMP},
      </if>
      <if test="createStaffId != null">
        CREATE_STAFF_ID = #{createStaffId,jdbcType=VARCHAR},
      </if>
      <if test="cycleValue != null">
        CYCLE_VALUE = #{cycleValue,jdbcType=VARCHAR},
      </if>
    </set>
    where POLICY_CYCLE_ID = #{policyCycleId,jdbcType=VARCHAR}
  </update>
  <update id="updateByPrimaryKey" parameterType="com.x.ic.msg.dao.mapper.bo.StlPolicyTaskCycle">
    <!--
      WARNING - @mbg.generated
      This element is automatically generated by MyBatis Generator, do not modify.
      This element was generated on Fri Aug 03 16:38:50 CST 2018.
    -->
    update stl_policy_task_cycle
    set POLICY_CYCLE_CODE = #{policyCycleCode,jdbcType=VARCHAR},
      POLICY_ID = #{policyId,jdbcType=BIGINT},
      OBJECT_TYPE = #{objectType,jdbcType=VARCHAR},
      OBJECT_CODE = #{objectCode,jdbcType=VARCHAR},
      START_TIME = #{startTime,jdbcType=TIMESTAMP},
      END_TIME = #{endTime,jdbcType=TIMESTAMP},
      STATUS = #{status,jdbcType=VARCHAR},
      TENANT_ID = #{tenantId,jdbcType=VARCHAR},
      CREATE_DATE = #{createDate,jdbcType=TIMESTAMP},
      UPDATE_TIME = #{updateTime,jdbcType=TIMESTAMP},
      CREATE_STAFF_ID = #{createStaffId,jdbcType=VARCHAR},
      CYCLE_VALUE = #{cycleValue,jdbcType=VARCHAR}
    where POLICY_CYCLE_ID = #{policyCycleId,jdbcType=VARCHAR}
  </update>
</mapper>